smart_format/__init__.py
smart_format/formatter.py
smart_format-0.0.1.dist-info/DESCRIPTION.rst
smart_format-0.0.1.dist-info/METADATA
smart_format-0.0.1.dist-info/RECORD
smart_format-0.0.1.dist-info/WHEEL
smart_format-0.0.1.dist-info/metadata.json
smart_format-0.0.1.dist-info/top_level.txt
