Metadata-Version: 2.0
Name: smart-format
Version: 0.0.1
Summary: Smart Formatter
Home-page: https://github.com/jmcs/smart-format
Author: João Santos
Author-email: jmcs@jsantos.eu
License: MIT License
Platform: UNKNOWN
Classifier: Programming Language :: Python
Classifier: Programming Language :: Python :: 2.7
Classifier: Programming Language :: Python :: 3.4
Classifier: Programming Language :: Python :: 3.5
Classifier: Development Status :: 4 - Beta
Classifier: Intended Audience :: Developers
Classifier: Operating System :: OS Independent
